LICENSE
README.md
pyproject.toml
setup.py
src/onespace/__init__.py
src/onespace.egg-info/PKG-INFO
src/onespace.egg-info/SOURCES.txt
src/onespace.egg-info/dependency_links.txt
src/onespace.egg-info/requires.txt
src/onespace.egg-info/top_level.txt
src/onespace/pytorch/__init__.py
src/onespace/pytorch/cv/__init__.py
src/onespace/pytorch/cv/callbacks.py
src/onespace/pytorch/cv/common.py
src/onespace/pytorch/cv/data_management.py
src/onespace/pytorch/cv/model.py
src/onespace/pytorch/cv/model_classes.py
src/onespace/pytorch/cv/model_zoo.py
src/onespace/pytorch/cv/param_selection.py
src/onespace/tabular/__init__.py
src/onespace/tabular/classification/__init__.py
src/onespace/tabular/classification/common.py
src/onespace/tabular/classification/logs.py
src/onespace/tabular/classification/model.py
src/onespace/tabular/classification/model_training.py
src/onespace/tabular/classification/param_selection.py
src/onespace/tensorflow/__init__.py
src/onespace/tensorflow/cv/__init__.py
src/onespace/tensorflow/cv/callbacks.py
src/onespace/tensorflow/cv/common.py
src/onespace/tensorflow/cv/data_management.py
src/onespace/tensorflow/cv/model.py
src/onespace/tensorflow/cv/model_zoo.py
src/onespace/tensorflow/cv/param_selection.py