Metadata-Version: 2.1
Name: onespace
Version: 0.0.0
Summary: A high-level python Framework with low-code support for Machine and Deep Learning
Home-page: https://github.com/Hassi34/onespace
Author: Hassi34
Author-email: hasnainmehmood3435@gmail.com
License: UNKNOWN
Project-URL: Bug Tracker, https://github.com/Hassi34/onespace/issues
Platform: UNKNOWN
Classifier: Programming Language :: Python :: 3
Classifier: License :: OSI Approved :: MIT License
Classifier: Operating System :: OS Independent
Requires-Python: >=3.7
License-File: LICENSE
